rmcc/__init__.py
rmcc/exception.py
rmcc/rmcc.py
rmcc-0.1.0.dist-info/LICENSE
rmcc-0.1.0.dist-info/METADATA
rmcc-0.1.0.dist-info/WHEEL
rmcc-0.1.0.dist-info/RECORD
