Metadata-Version: 2.1
Name: rmcc
Version: 0.1.0
Summary: The rmcc is Regional Mesh Code Calculator.
Author: otoani
Author-email: otoani11541@gmail.com
Requires-Python: >=3.12,<4.0
Classifier: Programming Language :: Python :: 3
Classifier: Programming Language :: Python :: 3.12
